MANIFEST.in
README.rst
setup.py
collective/.DS_Store
collective/__init__.py
collective/__init__.pyc
collective.ptg.thumbnailzoom.egg-info/PKG-INFO
collective.ptg.thumbnailzoom.egg-info/SOURCES.txt
collective.ptg.thumbnailzoom.egg-info/dependency_links.txt
collective.ptg.thumbnailzoom.egg-info/entry_points.txt
collective.ptg.thumbnailzoom.egg-info/namespace_packages.txt
collective.ptg.thumbnailzoom.egg-info/not-zip-safe
collective.ptg.thumbnailzoom.egg-info/requires.txt
collective.ptg.thumbnailzoom.egg-info/top_level.txt
collective/ptg/.DS_Store
collective/ptg/__init__.py
collective/ptg/__init__.pyc
collective/ptg/thumbnailzoom/.DS_Store
collective/ptg/thumbnailzoom/__init__.py
collective/ptg/thumbnailzoom/__init__.pyc
collective/ptg/thumbnailzoom/configure.zcml
collective/ptg/thumbnailzoom/i18n.sh
collective/ptg/thumbnailzoom/thumbnailzoom.pt
collective/ptg/thumbnailzoom/locales/.DS_Store
collective/ptg/thumbnailzoom/locales/collective.ptg.thumbnailzoom.pot
collective/ptg/thumbnailzoom/locales/collective.ptg.thumbnailzoon.pot
collective/ptg/thumbnailzoom/locales/manual.pot
collective/ptg/thumbnailzoom/locales/de/LC_MESSAGES/collective.ptg.thumbnailzoom.mo
collective/ptg/thumbnailzoom/locales/de/LC_MESSAGES/collective.ptg.thumbnailzoom.po
collective/ptg/thumbnailzoom/locales/es/LC_MESSAGES/collective.ptg.thumbnailzoom.mo
collective/ptg/thumbnailzoom/locales/es/LC_MESSAGES/collective.ptg.thumbnailzoom.po
collective/ptg/thumbnailzoom/locales/eu/LC_MESSAGES/collective.ptg.thumbnailzoom.po
collective/ptg/thumbnailzoom/locales/fi/LC_MESSAGES/collective.ptg.thumbnailzoom.po
collective/ptg/thumbnailzoom/locales/fr/LC_MESSAGES/collective.ptg.thumbnailzoom.mo
collective/ptg/thumbnailzoom/locales/fr/LC_MESSAGES/collective.ptg.thumbnailzoom.po
collective/ptg/thumbnailzoom/locales/it/LC_MESSAGES/collective.ptg.thumbnailzoom.po
collective/ptg/thumbnailzoom/locales/nl/LC_MESSAGES/collective.ptg.thumbnailzoom.po
collective/ptg/thumbnailzoom/locales/no/.DS_Store
collective/ptg/thumbnailzoom/locales/no/LC_MESSAGES/.DS_Store
collective/ptg/thumbnailzoom/locales/no/LC_MESSAGES/collective.ptg.thumbnailzoom.mo
collective/ptg/thumbnailzoom/locales/no/LC_MESSAGES/collective.ptg.thumbnailzoom.po
collective/ptg/thumbnailzoom/locales/pt_BR/LC_MESSAGES/collective.ptg.thumbnailzoom.po
collective/ptg/thumbnailzoom/resources/style.css
docs/HISTORY.txt
docs/INSTALL.txt
docs/LICENSE.GPL
docs/LICENSE.txt