Metadata-Version: 1.0
Name: collective.ptg.thumbnailzoom
Version: 1.0.5.1
Summary: Adds a 'thumbnailzoom' view to collective.plonetruegallery
Home-page: https://github.com/collective/collective.ptg.thumbnailzoom
Author: Nathan Van Gheem
Author-email: vangheem@gmail.com
License: GPL
Keywords: plone plonetruegallery addon
Platform: UNKNOWN
Classifier: Framework :: Plone
Classifier: Programming Language :: Python
